telepoller/__init__.py
telepoller-0.0.3.dist-info/METADATA
telepoller-0.0.3.dist-info/WHEEL
telepoller-0.0.3.dist-info/top_level.txt
telepoller-0.0.3.dist-info/RECORD
