Metadata-Version: 2.1
Name: telepoller
Version: 0.0.3
Summary: Poller for Telegram Bot on Pytelegrambotapi
Author: STaper_Admin
Classifier: Programming Language :: Python :: 3.10
Classifier: License :: OSI Approved :: MIT License
Classifier: Operating System :: OS Independent
Requires-Python: >=3.10
Requires-Dist: pytelegrambotapi
